cosmo_ml_tools/__init__.py
cosmo_ml_tools/common.py
cosmo_ml_tools/cosmo_ml_tools.py
cosmo_ml_tools-0.0.1.dist-info/LICENSE
cosmo_ml_tools-0.0.1.dist-info/METADATA
cosmo_ml_tools-0.0.1.dist-info/WHEEL
cosmo_ml_tools-0.0.1.dist-info/entry_points.txt
cosmo_ml_tools-0.0.1.dist-info/top_level.txt
cosmo_ml_tools-0.0.1.dist-info/RECORD
